[
  {
    "name": "APPINSIGHTS_INSTRUMENTATIONKEY",
    "value": "04712763-a0d4-49b0-9b3c-137b3f798509",
    "slotSetting": false
  },
  {
    "name": "APPLICATIONINSIGHTS_CONNECTION_STRING",
    "value": "InstrumentationKey=04712763-a0d4-49b0-9b3c-137b3f798509;IngestionEndpoint=https://eastus2-3.in.applicationinsights.azure.com/;LiveEndpoint=https://eastus2.livediagnostics.monitor.azure.com/;ApplicationId=c1d6b9a6-ffdf-437c-8428-adb1c0d4df19",
    "slotSetting": false
  },
  {
    "name": "BLOB_SALESFORCE_ACCOUNT_NAME",
    "value": "ecfmgqa001",
    "slotSetting": false
  },
  {
    "name": "BLOB_SALESFORCE_ACCOUNT_KEY",
    "value": "@Microsoft.KeyVault(SecretUri=https://corp-qa-kv.vault.azure.net/secrets/DVI-BLOB-SALESFORCE-ACCOUNT-KEY)",
    "slotSetting": false
  },
  {
    "name": "CONFIG_VERSION",
    "value": "0.3",
    "slotSetting": false
  },
  {
    "name": "DATABASE_URL",
    "value": "@Microsoft.KeyVault(SecretUri=https://corp-qa-kv.vault.azure.net/secrets/DVI-POSTGRES-CONNECTION-STRING)",
    "slotSetting": false
  },  
  {
    "name": "FEATURE_FLAG_BLOB_NAME",
    "value": "DVI_Feature_Flag_QA.json",
    "slotSetting": false
  },
  {
    "name": "GRAPHQL_SERVICE_JWT_EXPIRES_IN",
    "value": "3000s",
    "slotSetting": false
  },
  {
    "name": "GRAPHQL_SERVICE_URL",
    "value": "https://data.dvi-qa.myintealth.app/api/graphql",
    "slotSetting": false
  },
  {
    "name": "NODE_ENV",
    "value": "production",
    "slotSetting": false
  },
  {
    "name": "SF_OIDC_AUDIENCE",
    "value": "3MVG9AJuBE3rTYDgSigxi9GX743f1P_TVvLNjg58HQtgadUwJ8hgnATkVWSuWFy0f5CvgVTHxAHMnfcmt8yH7",
    "slotSetting": false
  },
  {
    "name": "SF_OIDC_CLOCK_TOLERANCE",
    "value": "4 hours",
    "slotSetting": false
  },
  {
    "name": "SF_OIDC_ENDPOINT",
    "value": "https://myintealth--dataqa.sandbox.my.salesforce.com/id/keys",
    "slotSetting": false
  },
  {
    "name": "SF_OIDC_IGNORE_ISSUER",
    "value": "false",
    "slotSetting": false
  },
  {
    "name": "SF_OIDC_ISSUER",
    "value": "https://myintealth--dataqa.sandbox.my.salesforce.com",
    "slotSetting": false
  }
]